{
	"backtraceGraph" : 
	{
		"commands" : 
		[
			"INSTALL"
		],
		"files" : 
		[
			"external/bullet/src/BulletCollision/CMakeLists.txt"
		],
		"nodes" : 
		[
			{
				"file" : 0
			},
			{
				"command" : 0,
				"file" : 0,
				"line" : 271,
				"parent" : 0
			},
			{
				"command" : 0,
				"file" : 0,
				"line" : 274,
				"parent" : 0
			},
			{
				"command" : 0,
				"file" : 0,
				"line" : 276,
				"parent" : 0
			}
		]
	},
	"installers" : 
	[
		{
			"backtrace" : 1,
			"component" : "Unspecified",
			"destination" : "lib",
			"paths" : 
			[
				"external/bullet/src/BulletCollision/libBulletCollision.a"
			],
			"targetId" : "BulletCollision::@fdb645dca4c11a1eb010",
			"targetIndex" : 1,
			"type" : "target"
		},
		{
			"backtrace" : 2,
			"component" : "Unspecified",
			"destination" : "include/bullet",
			"paths" : 
			[
				"external/bullet/src/BulletCollision"
			],
			"type" : "directory"
		},
		{
			"backtrace" : 3,
			"component" : "Unspecified",
			"destination" : "include/bullet/BulletCollision",
			"paths" : 
			[
				"external/bullet/src/BulletCollision/../btBulletCollisionCommon.h"
			],
			"type" : "file"
		}
	],
	"paths" : 
	{
		"build" : "external/bullet/src/BulletCollision",
		"source" : "external/bullet/src/BulletCollision"
	}
}
